multiconsumers_queue/__init__.py
multiconsumers_queue/helpers.py
multiconsumers_queue/wrapper.py
multiconsumers_queue-0.1.4.dist-info/LICENSE
multiconsumers_queue-0.1.4.dist-info/WHEEL
multiconsumers_queue-0.1.4.dist-info/METADATA
multiconsumers_queue-0.1.4.dist-info/RECORD
