Metadata-Version: 2.1
Name: multiconsumers-queue
Version: 0.1.4
Summary: Wrapper for queue based producer/consumers parallel tasks execution
Home-page: https://github.com/IaroslavR/multiconsumers-queue
License: MIT
Keywords: threading,queue,wrapper
Author: Iaroslav Russkykh
Author-email: iarruss@ya.ru
Requires-Python: >=3.7,<3.8
Classifier: License :: OSI Approved :: MIT License
Classifier: Programming Language :: Python :: 3
Classifier: Programming Language :: Python :: 3.7
Provides-Extra: click
Provides-Extra: dev
Provides-Extra: docs
Requires-Dist: arrow (>=0.15.5,<0.16.0)
Requires-Dist: attrs (>=19.3.0,<20.0.0)
Requires-Dist: black (>=19.10b0,<20.0); extra == "dev"
Requires-Dist: click (>=7.1.1,<8.0.0); extra == "click"
Requires-Dist: coverage (>=5.1,<6.0); extra == "dev"
Requires-Dist: darglint (>=1.2.3,<2.0.0); extra == "dev"
Requires-Dist: flake8 (>=3.7.9,<4.0.0); extra == "dev"
Requires-Dist: flake8-annotations (>=2.1.0,<3.0.0); extra == "dev"
Requires-Dist: flake8-bandit (>=2.1.2,<3.0.0); extra == "dev"
Requires-Dist: flake8-black (>=0.1.1,<0.2.0); extra == "dev"
Requires-Dist: flake8-bugbear (>=20.1.4,<21.0.0); extra == "dev"
Requires-Dist: flake8-docstrings (>=1.5.0,<2.0.0); extra == "dev"
Requires-Dist: flake8-import-order (>=0.18.1,<0.19.0); extra == "dev"
Requires-Dist: loguru (>=0.4.1,<0.5.0)
Requires-Dist: m2r (>=0.2.1,<0.3.0); extra == "docs"
Requires-Dist: mypy (>=0.770,<0.771); extra == "dev"
Requires-Dist: pre-commit (>=2.3.0,<3.0.0); extra == "dev"
Requires-Dist: pytest (>=5.4.1,<6.0.0); extra == "dev"
Requires-Dist: pytype (>=2020.4.22,<2021.0.0); extra == "dev"
Requires-Dist: safety (>=1.8.7,<2.0.0); extra == "dev"
Requires-Dist: sphinx (==2.3.1); extra == "docs"
Requires-Dist: sphinx-autodoc-typehints (>=1.10.3,<2.0.0); extra == "docs"
Requires-Dist: sphinx-rtd-theme (>=0.4.3,<0.5.0); extra == "docs"
Requires-Dist: toml (>=0.10.0,<0.11.0); extra == "dev" or extra == "docs"
Requires-Dist: typeguard (>=2.7.1,<3.0.0); extra == "dev"
Project-URL: Documentation, http://multiconsumers-queue.rtfd.io/
Project-URL: Repository, https://github.com/IaroslavR/multiconsumers-queue
Project-URL: issues, https://github.com/IaroslavR/multiconsumers-queue-cli/issues
